tiny_queue/__init__.py
tiny_queue/async_queue.py
tiny_queue/base.py
tiny_queue/decorators.py
tiny_queue/fifo.py
tiny_queue/monitor.py
tiny_queue/persistent.py
tiny_queue/priority.py
tiny_queue/utils.py
tiny_queue-0.1.0.dist-info/licenses/LICENSE
tiny_queue-0.1.0.dist-info/METADATA
tiny_queue-0.1.0.dist-info/WHEEL
tiny_queue-0.1.0.dist-info/top_level.txt
tiny_queue-0.1.0.dist-info/RECORD
